maap/AWS.py
maap/Dictlist.py
maap/Profile.py
maap/Result.py
maap/Secrets.py
maap/__init__.py
maap/config_reader.py
maap/dps/DpsHelper.py
maap/dps/__init__.py
maap/dps/dps_job.py
maap/dps/execute.xml
maap/dps/execute_inputs.xml
maap/maap.py
maap/singleton.py
maap/utils/CMR.py
maap/utils/Presenter.py
maap/utils/__init__.py
maap/utils/algorithm_utils.py
maap/utils/endpoints.py
maap/utils/job.py
maap/utils/requests_utils.py
maap/xmlParser.py
maap_py-4.2.0.dist-info/LICENSE
maap_py-4.2.0.dist-info/METADATA
maap_py-4.2.0.dist-info/WHEEL
maap_py-4.2.0.dist-info/RECORD
