Metadata-Version: 2.1
Name: maap-py
Version: 4.2.0
Summary: Python client API for interacting with the NASA MAAP API
Home-page: https://github.com/MAAP-Project/maap-py
License: Apache-2.0
Keywords: dataset,granule,nasa,MAAP,CMR
Author: Jet Propulsion Laboratory
Author-email: jpl@nasa.gov
Requires-Python: >=3.9,<4.0
Classifier: Development Status :: 3 - Alpha
Classifier: Environment :: Console
Classifier: Framework :: Pytest
Classifier: Intended Audience :: Developers
Classifier: Intended Audience :: Information Technology
Classifier: Intended Audience :: Science/Research
Classifier: License :: OSI Approved :: Apache Software License
Classifier: Operating System :: OS Independent
Classifier: Programming Language :: Python :: 3
Classifier: Programming Language :: Python :: 3.9
Classifier: Programming Language :: Python :: 3.10
Classifier: Programming Language :: Python :: 3.11
Classifier: Programming Language :: Python :: 3.12
Classifier: Programming Language :: Python :: 2.7
Classifier: Programming Language :: Python :: 3.5
Classifier: Topic :: Internet :: WWW/HTTP
Classifier: Topic :: Scientific/Engineering
Classifier: Topic :: Software Development :: Libraries :: Python Modules
Requires-Dist: backoff (>=2.2.1,<3.0.0)
Requires-Dist: boto3 (>=1.34.139,<2.0.0)
Requires-Dist: configparser (>=7.0.0,<8.0.0)
Requires-Dist: importlib-resources (>=6.4.0,<7.0.0)
Requires-Dist: mapboxgl (>=0.10.2,<0.11.0)
Requires-Dist: pyyaml (>=6.0.1,<7.0.0)
Requires-Dist: requests (>=2.32.3,<3.0.0)
Project-URL: Repository, https://github.com/MAAP-Project/maap-py
